dwave/plugins/qiskit/__init__.py
dwave/plugins/qiskit/package_info.py
dwave/plugins/qiskit/minimum_eigen_solvers/__init__.py
dwave/plugins/qiskit/minimum_eigen_solvers/dwave_minimum_eigen_solver.py
dwave_qiskit_plugin-0.1.0.dist-info/LICENSE
dwave_qiskit_plugin-0.1.0.dist-info/METADATA
dwave_qiskit_plugin-0.1.0.dist-info/WHEEL
dwave_qiskit_plugin-0.1.0.dist-info/top_level.txt
dwave_qiskit_plugin-0.1.0.dist-info/RECORD
