Metadata-Version: 2.1
Name: dwave-qiskit-plugin
Version: 0.1.0
Summary: Access D-Wave system from IBM Qiskit via MinimumEigensolver interface.
Home-page: https://github.com/dwavesystems/dwave-qiskit-plugin
Author: D-Wave Systems Inc.
Author-email: radomir@dwavesys.com
License: Apache 2.0
Platform: UNKNOWN
Classifier: License :: OSI Approved :: Apache Software License
Classifier: Operating System :: OS Independent
Classifier: Programming Language :: Python :: 3 :: Only
Classifier: Programming Language :: Python :: 3.6
Classifier: Programming Language :: Python :: 3.7
Classifier: Programming Language :: Python :: 3.8
Requires-Python: >=3.6
